LICENSE
MANIFEST.in
README.rst
setup.py
django_hashphrase.egg-info/PKG-INFO
django_hashphrase.egg-info/SOURCES.txt
django_hashphrase.egg-info/dependency_links.txt
django_hashphrase.egg-info/top_level.txt
hashphrase/__init__.py
hashphrase/admin.py
hashphrase/helpers.py
hashphrase/models.py
hashphrase/urls.py
hashphrase/views.py