Metadata-Version: 1.1
Name: django-hashphrase
Version: 0.4
Summary: A Django app to facilitate email links
Home-page: n/a
Author: Pei-Wei Wu
Author-email: peiwei.wu@gmail.com
License: BSD License
Download-URL: https://github.com/peiwei/django-hashlink/tarball/0.1
Platform: UNKNOWN
Classifier: Environment :: Web Environment
Classifier: Framework :: Django
Classifier: Intended Audience :: Developers
Classifier: License :: OSI Approved :: BSD License
Classifier: Operating System :: OS Independent
Classifier: Programming Language :: Python
Classifier: Programming Language :: Python :: 3
Classifier: Programming Language :: Python :: 3.2
Classifier: Programming Language :: Python :: 3.3
Classifier: Topic :: Internet :: WWW/HTTP
Classifier: Topic :: Internet :: WWW/HTTP :: Dynamic Content
